[
  {
    "id": 10001,
    "priority": 0,
    "startedAt": 1501491600,
    "endedAt": 1893423600,
    "closedAt": 1893423600,
    "imageId": 0,
    "name": ""
  },
  {
    "id": 100198,
    "priority": 0,
    "startedAt": 1588518000,
    "endedAt": 1589122799,
    "closedAt": 1589727599,
    "imageId": 0,
    "name": ""
  },
  {
    "id": 100199,
    "priority": 0,
    "startedAt": 1589122800,
    "endedAt": 1589727599,
    "closedAt": 1590332399,
    "imageId": 0,
    "name": ""
  },
  {
    "id": 200081,
    "priority": 0,
    "startedAt": 1588150800,
    "endedAt": 1590937199,
    "closedAt": 1591541999,
    "imageId": 0,
    "name": ""
  }
]